setup.py
blog/__init__.py
blog/downloader.py
blogdownloader.egg-info/PKG-INFO
blogdownloader.egg-info/SOURCES.txt
blogdownloader.egg-info/dependency_links.txt
blogdownloader.egg-info/top_level.txt